google_cloud_debugger_client-1.7.0-py3.9-nspkg.pth
google/cloud/debugger/__init__.py
google/cloud/debugger/gapic_version.py
google/cloud/debugger/py.typed
google/cloud/debugger_v2/__init__.py
google/cloud/debugger_v2/gapic_metadata.json
google/cloud/debugger_v2/gapic_version.py
google/cloud/debugger_v2/py.typed
google/cloud/debugger_v2/services/__init__.py
google/cloud/debugger_v2/services/controller2/__init__.py
google/cloud/debugger_v2/services/controller2/async_client.py
google/cloud/debugger_v2/services/controller2/client.py
google/cloud/debugger_v2/services/controller2/transports/__init__.py
google/cloud/debugger_v2/services/controller2/transports/base.py
google/cloud/debugger_v2/services/controller2/transports/grpc.py
google/cloud/debugger_v2/services/controller2/transports/grpc_asyncio.py
google/cloud/debugger_v2/services/controller2/transports/rest.py
google/cloud/debugger_v2/services/debugger2/__init__.py
google/cloud/debugger_v2/services/debugger2/async_client.py
google/cloud/debugger_v2/services/debugger2/client.py
google/cloud/debugger_v2/services/debugger2/transports/__init__.py
google/cloud/debugger_v2/services/debugger2/transports/base.py
google/cloud/debugger_v2/services/debugger2/transports/grpc.py
google/cloud/debugger_v2/services/debugger2/transports/grpc_asyncio.py
google/cloud/debugger_v2/services/debugger2/transports/rest.py
google/cloud/debugger_v2/types/__init__.py
google/cloud/debugger_v2/types/controller.py
google/cloud/debugger_v2/types/data.py
google/cloud/debugger_v2/types/debugger.py
google_cloud_debugger_client-1.7.0.dist-info/LICENSE
google_cloud_debugger_client-1.7.0.dist-info/METADATA
google_cloud_debugger_client-1.7.0.dist-info/WHEEL
google_cloud_debugger_client-1.7.0.dist-info/namespace_packages.txt
google_cloud_debugger_client-1.7.0.dist-info/top_level.txt
google_cloud_debugger_client-1.7.0.dist-info/RECORD
