Metadata-Version: 2.1
Name: google-cloud-debugger-client
Version: 1.7.0
Summary: Google Cloud Debugger Client API client library
Home-page: https://github.com/googleapis/python-debugger-client
Author: Google LLC
Author-email: googleapis-packages@google.com
License: Apache 2.0
Platform: Posix; MacOS X; Windows
Classifier: Development Status :: 5 - Production/Stable
Classifier: Intended Audience :: Developers
Classifier: License :: OSI Approved :: Apache Software License
Classifier: Programming Language :: Python
Classifier: Programming Language :: Python :: 3
Classifier: Programming Language :: Python :: 3.7
Classifier: Programming Language :: Python :: 3.8
Classifier: Programming Language :: Python :: 3.9
Classifier: Programming Language :: Python :: 3.10
Classifier: Programming Language :: Python :: 3.11
Classifier: Operating System :: OS Independent
Classifier: Topic :: Internet
Requires-Python: >=3.7
License-File: LICENSE
Requires-Dist: google-api-core[grpc] (!=2.0.*,!=2.1.*,!=2.10.*,!=2.2.*,!=2.3.*,!=2.4.*,!=2.5.*,!=2.6.*,!=2.7.*,!=2.8.*,!=2.9.*,<3.0.0dev,>=1.34.0)
Requires-Dist: proto-plus (<2.0.0dev,>=1.22.0)
Requires-Dist: protobuf (!=3.20.0,!=3.20.1,!=4.21.0,!=4.21.1,!=4.21.2,!=4.21.3,!=4.21.4,!=4.21.5,<5.0.0dev,>=3.19.5)
Requires-Dist: google-cloud-source-context (<2.0.0dev,>=1.0.0)
Requires-Dist: proto-plus (<2.0.0dev,>=1.22.2) ; python_version >= "3.11"
